Workbook
Name qn: #REF!
Name qo210.: #REF!
Name QO21O: #REF!
Name TOTALD.21: #REF!
Name TOTALOFERTA: #REF!
Name TOTALP.1: #REF!
Name TOTALP.2: #REF!
Name TOTALP.3: #REF!
Name TOTALP.31HOG: #REF!
Name TOTALP.5: #REF!
Name TOTALP.51: #REF!
Name TOTALP.52: #REF!
Name TOTALP.6: #REF!
Name TOTALP.7: #REF!
Name TOTALP2EQ: #REF!
Name TOTALP31ISFLSH: #REF!
Name TOTALP3GOB: #REF!
Name TOTALUTILIZ.1: #REF!

Sheet sets
A1: ac | B1: a(ac) | C1: c(ac) | D1: ins(ac)
A2: a-agr | B2: a-agr | C2: c-agr | D2: hhd
A3: a-min | B3: a-min | C3: c-min | D3: gov
A4: a-food | B4: a-food | C4: c-food | D4: row
A5: a-refpet | B5: a-refpet | C5: c-refpet
A6: a-maq | B6: a-maq | C6: c-maq
A7: a-othmnfc | B7: a-othmnfc | C7: c-othmnfc
A8: a-othind | B8: a-othind | C8: c-othind
A9: a-trdtrns | B9: a-trdtrns | C9: c-trdtrns
A10: a-admpub | B10: a-admpub | C10: c-admpub
A11: a-othsvc | B11: a-othsvc | C11: c-othsvc
A12: c-agr
A13: c-min
A14: c-food
A15: c-refpet
A16: c-maq
A17: c-othmnfc
A18: c-othind
A19: c-trdtrns
A20: c-admpub
A21: c-othsvc
A22: lab
A23: cap
... A34: total

Sheet SAM
A1: SAM Costa Rica 2012; 10000 x millones de colones; Source: en base a Cicowiez et al. (2017)
B2: a-agr | C2: a-min | D2: a-food | E2: a-refpet | F2: a-maq | G2: a-othmnfc | H2: a-othind | I2: a-trdtrns | J2: a-admpub | K2: a-othsvc | L2: c-agr | M2: c-min | N2: c-food | O2: c-refpet | P2: c-maq | Q2: c-othmnfc | R2: c-othind | S2: c-trdtrns | T2: c-admpub | U2: c-othsvc | V2: lab | W2: cap | X2: tax-act | Y2: tax-imp | Z2: tax-exp | AA2: tax-com | AB2: tax-dir | AC2: hhd | AD2: gov | AE2: row | AF2: sav-inv | AG2: dstk | AH2: total
A3: a-agr | L3: 253.08087 | N3: 5.9348687 | Q3: 0.94907799 | R3: 0.00066524865 | S3: 0.10959032 | U3: 0.28630703 | AH3: =SUM(B3:AG3) -> 260.36138
A4: a-min | M4: 13.002556 | Q4: 0.0050559348 | S4: 0.066927632 | U4: 0.031393523 | AH4: =SUM(B4:AG4) -> 13.105933
A5: a-food | L5: 8.990791 | N5: 377.19746 | Q5: 6.113386 | R5: 0.029963581 | S5: 3.4771157 | U5: 2.2437151 | AH5: =SUM(B5:AG5) -> 398.05243
A6: a-refpet | O6: 0.083455062 | Q6: 18.339253 | S6: 0.70062992 | AH6: =SUM(B6:AG6) -> 19.123338
A7: a-maq | P7: 108.13043 | Q7: 31.953342 | R7: 0.086796473 | S7: 0.99241972 | U7: 6.8437653 | AH7: =SUM(B7:AG7) -> 148.00675
A8: a-othmnfc | L8: 0.022058045 | M8: 0.1101229 | N8: 0.076099669 | O8: 0.050710566 | P8: 0.41895376 | Q8: 288.09202 | R8: 0.53367764 | S8: 2.6667528 | U8: 6.4815131 | AH8: =SUM(B8:AG8) -> 298.45191
A9: a-othind | Q9: 0.024625806 | R9: 475.19283 | S9: 0.27883735 | U9: 1.077374 | AH9: =SUM(B9:AG9) -> 476.57367
A10: a-trdtrns | O10: 0.69143366 | Q10: 0.4469288 | R10: 0.043743039 | S10: 538.70215 | U10: 12.323877 | AH10: =SUM(B10:AG10) -> 552.20813
A11: a-admpub | L11: 0.087664447 | N11: 0.05598761 | Q11: 0.17736082 | R11: 0.0014205439 | S11: 1.3281373 | T11: 70.271488 | U11: 3.5418416 | AH11: =SUM(B11:AG11) -> 75.4639
A12: a-othsvc | L12: 0.045999637 | M12: 0.013982472 | N12: 0.023708105 | P12: 0.065825914 | Q12: 7.4573528 | R12: 3.0247488 | S12: 5.8463772 | U12: 1666.8619 | AH12: =SUM(B12:AG12) -> 1683.3399
A13: c-agr | B13: 24.096417 | C13: 0.00027174987 | D13: 114.20248 | E13: 4.2286975e-22 | F13: 0.0027630597 | G13: 2.9695417 | H13: 0.017807706 | I13: 0.025494786 | J13: 0.047521628 | K13: 12.582306 | AC13: 39.653213 | AD13: 0.020439977 | AE13: 103.97597 | AF13: 5.3673916 | AG13: -0.055262811 | AH13: =SUM(B13:AG13) -> 302.90635
A14: c-min | B14: 0.2488588 | C14: 0.68327529 | D14: 0.3151777 | E14: 0.13047429 | F14: 0.022481835 | G14: 2.8211105 | H14: 12.694996 | I14: 0.25930602 | K14: 0.78377034 | AC14: 0.21002306 | AE14: 0.20559737 | AG14: -0.0078239097 | AH14: =SUM(B14:AG14) -> 18.367247
A15: c-food | B15: 11.809594 | C15: 0.0026291359 | D15: 43.74059 | E15: 0.046780912 | F15: 0.017991894 | G15: 2.1069811 | H15: 0.61911802 | I15: 0.25701816 | J15: 0.22204969 | K15: 39.276786 | AC15: 254.91956 | AD15: 0.67231199 | AE15: 116.62017 | AG15: 1.079186 | AH15: =SUM(B15:AG15) -> 471.39077
A16: c-refpet | B16: 11.270116 | C16: 1.3292527 | D16: 6.5597406 | E16: 0.14616821 | F16: 0.18881999 | G16: 6.7829719 | H16: 12.489787 | I16: 38.978535 | J16: 0.56890302 | K16: 15.977592 | AC16: 63.876127 | AE16: 0.092175572 | AG16: -8.0111097 | AH16: =SUM(B16:AG16) -> 150.24908
A17: c-maq | B17: 1.3020437 | C17: 0.53854062 | D17: 1.262108 | E17: 0.011428609 | F17: 14.729236 | G17: 1.9230017 | H17: 25.253187 | I17: 5.2829876 | J17: 0.18441991 | K17: 11.10132 | AC17: 87.885676 | AD17: 0.34485244 | AE17: 103.78506 | AF17: 106.85405 | AG17: -5.8607485 | AH17: =SUM(B17:AG17) -> 354.59716
A18: c-othmnfc | B18: 36.172793 | C18: 0.33067356 | D18: 29.235305 | E18: 9.239979 | F18: 32.30815 | G18: 98.29294 | H18: 95.477863 | I18: 14.926479 | J18: 1.5494162 | K18: 50.39331 | AC18: 182.76704 | AD18: 8.9884724 | AE18: 150.66412 | AF18: 15.275914 | AG18: 10.35161 | AH18: =SUM(B18:AG18) -> 735.97406
A19: c-othind | B19: 4.9282978 | C19: 0.46093212 | D19: 7.5550519 | E19: 0.37599488 | F19: 3.0529549 | G19: 7.7350826 | H19: 48.501768 | I19: 14.988849 | J19: 1.966575 | K19: 45.243044 | AC19: 44.583818 | AE19: 0.51131271 | AF19: 303.07705 | AH19: =SUM(B19:AG19) -> 482.98073
A20: c-trdtrns | B20: 27.2458 | C20: 1.2508627 | D20: 41.481575 | E20: 2.3875787 | F20: 15.70907 | G20: 35.326932 | H20: 37.051658 | I20: 53.467269 | J20: 1.0852861 | K20: 52.399168 | AC20: 231.79332 | AD20: 2.6967773 | AE20: 39.234156 | AF20: 36.154553 | AG20: -0.26635077 | AH20: =SUM(B20:AG20) -> 577.01766
A21: c-admpub | AC21: 0.25884826 | AD21: 70.01264 | AH21: =SUM(B21:AG21) -> 70.271488
A22: c-othsvc | B22: 16.863816 | C22: 1.678702 | D22: 32.702503 | E22: 0.79682473 | F22: 15.618473 | G22: 27.274568 | H22: 63.511408 | I22: 116.69393 | J22: 17.058331 | K22: 298.25671 | AC22: 642.32784 | AD22: 316.43022 | AE22: 223.11613 | AF22: 14.678467 | AH22: =SUM(B22:AG22) -> 1787.0079
A23: lab | B23: 76.243953 | C23: 1.8609191 | D23: 47.756943 | E23: 0.89638632 | F23: 25.436665 | G23: 57.368871 | H23: 90.745356 | I23: 195.9653 | J23: 51.634377 | K23: 719.23311 | AE23: -1.555335 | AH23: =SUM(B23:AG23) -> 1265.5865
A24: cap | B24: 46.78255 | C24: 4.7311429 | D24: 69.092484 | E24: 4.976883 | F24: 39.289704 | G24: 52.373535 | H24: 84.248773 | I24: 97.693889 | J24: 0.55768563 | K24: 406.46062 | AH24: =SUM(B24:AG24) -> 806.20726
A25: tax-act | B25: 3.3971395 | C25: 0.23873145 | D25: 4.1484738 | E25: 0.11483918 | F25: 1.6304387 | G25: 3.4763762 | H25: 5.9619461 | I25: 13.669071 | J25: 0.58933525 | K25: 31.632163 | AH25: =SUM(B25:AG25) -> 64.858514
A26: tax-imp | L26: 0.30390297 | M26: 0.2664048 | N26: 5.211008 | O26: 35.17574 | P26: 18.469231 | Q26: 10.743326 | R26: 7.1585234e-07 | AH26: =SUM(B26:AG26) -> 70.169613
A27: tax-exp | L27: 0.53766818 | N27: 0.32819355 | AH27: =SUM(B27:AG27) -> 0.86586174
A28: tax-com | L28: 1.1212359 | M28: 1.4677688 | N28: 25.399264 | O28: 0.90488607 | P28: 19.84516 | Q28: 37.242737 | R28: 3.5391001 | S28: 6.6855472 | U28: 31.691763 | AH28: =SUM(B28:AG28) -> 127.89746
A29: tax-dir | AC29: 102.25379 | AH29: =SUM(B29:AG29) -> 102.25379
A30: hhd | V30: 1265.5865 | W30: 806.20726 | AD30: -49.149379 | AE30: -54.682334 | AH30: =SUM(B30:AG30) -> 1967.9621
A31: gov | X31: 64.858514 | Y31: 70.169613 | Z31: 0.86586174 | AA31: 127.89746 | AB31: 102.25379 | AE31: 4.0043814 | AH31: =SUM(B31:AG31) -> 370.04962
A32: row | L32: 38.716162 | M32: 3.5064117 | N32: 57.164177 | O32: 113.34285 | P32: 207.66757 | Q32: 334.42959 | R32: 0.52778388 | S32: 16.163172 | U32: 55.624473 | AH32: =SUM(B32:AG32) -> 827.14219
A33: sav-inv | AC33: 317.43284 | AD33: 20.03329 | AE33: 141.1708 | AH33: =SUM(B33:AG33) -> 478.63693
A34: dstk | AF34: -2.7704993 | AH34: =SUM(B34:AG34) -> -2.7704993
A35: total | B35: =SUM(B3:B34) -> 260.36138 | C35: =SUM(C3:C34) -> 13.105933 | D35: =SUM(D3:D34) -> 398.05243 | E35: =SUM(E3:E34) -> 19.123338 | F35: =SUM(F3:F34) -> 148.00675 | G35: =SUM(G3:G34) -> 298.45191 | H35: =SUM(H3:H34) -> 476.57367 | I35: =SUM(I3:I34) -> 552.20813 | ... AH35: =SUM(AH3:AH34) -> 14954.309

Sheet tradelas
A1: tradelas(c,trdelas)
B2: sigma_Q | C2: sigma_X
A3: c-agr | B3: 2 | C3: 2
A4: c-min | B4: 2 | C4: 2
A5: c-food | B5: 2 | C5: 2
A6: c-refpet | B6: 2 | C6: 2
A7: c-maq | B7: 2 | C7: 2
A8: c-othmnfc | B8: 2 | C8: 2
A9: c-othind | B9: 2 | C9: 2
A10: c-trdtrns | B10: 2 | C10: 2
A11: c-admpub | B11: 2 | C11: 2
A12: c-othsvc | B12: 2 | C12: 2

Sheet layout
D1: rdim | E1: cdim
A2: set | B2: ac | C2: sets!a2 | D2: 1 | E2: 0
A3: set | B3: a | C3: sets!b2 | D3: 1 | E3: 0
A4: set | B4: c | C4: sets!c2 | D4: 1 | E4: 0
A5: set | B5: ins | C5: sets!d2 | D5: 1 | E5: 0
A6: par | B6: SAM | C6: SAM!A2 | D6: 1 | E6: 1
A7: par | B7: tradelas | C7: tradelas!A2 | D7: 1 | E7: 1

Sheet tables
A1: Tabla 1. Producto Bruto Interno (Año base, 2012) | E1: Tabla 2. Cuenta corriente de la balanza de pagos (Año base, 2012) | I1: Tabla 3. Presupuesto del gobierno (Año base, 2012) | M1: Tabla 4. Estructura sectorial (%) (Año base, 2012) | V1: Tabla 5. Intensidad de uso factorial (%) (Año base, 2012) | AA1: Tabla 6. Estructura de la demanda (%) (Año base, 2012) | AJ1: Tabla 7. Estructura de los ingresos de las instituciones (Año base, 2012)
A3: Ítem | B3: Nominal | C3: PBI Share (%) | E3: Ítem | F3: Nominal | G3: PBI Share (%) | I3: Ítem | J3: Nominal | K3: PBI Share (%) | M3: Producto | N3: VA Share | O3: VBP Share | P3: Empleo Share | Q3: Expo. Share | R3: Expo/Prod. | S3: Impo. Share | T3: Impo./Dem. | V3: Actividad | W3: Trabajo | X3: Capital | Y3: Total | AA3: Producto | AB3: Consumo Intermedio | AC3: Consumo Privado | AD3: Consumo Público | AE3: Formación Bruta de Capital | AF3: Variación de Existencias | AG3: Exportaciones | AH3: Total Demanda | AJ3: Ítem | AK3: Hogares | AL3: Gobierno | AM3: Resto del mundo
A4: Absorción | B4: =SUM(B5:B8) -> 2426.0781 | C4: =B4/$B$12 -> 1.038054 | E4: Exportaciones | F4: =SUM(SAM!AE13:AE22) -> 738.20468 | G4: =F4/$B$12 -> 0.31585806 | I4: Impuestos directos | J4: =SAM!AB31 -> 102.25379 | K4: =J4/$B$12 -> 0.043751665 | M4: c-agr | N4: =(SAM!$L$3/SAM!$AH$3*SUM(SAM!B$23:B$24)+SAM!$L$4/SAM!$AH$4*SUM(SAM!C$23:C$24)+SAM!$L$5/SAM!$AH$5*SUM(SAM!D$23:D$24)+SAM!$L$6/SAM!$AH$6*SUM(SAM!E$23:E$24)+SAM!$L$7/SAM!$AH$7*SUM(SAM!F$23:F$24)+SAM!$L$8/SAM!$AH$8*SUM(SAM!G$23:G$24)+SAM!$L$9/SAM!$AH$9*SUM(SAM!H$23:H$24)+SAM!$L$10/SAM!$AH$10*SUM(SAM!I$23:I$24)+SAM!$L$11/SAM!$AH$11*SUM(SAM!J$23:J$24)+SAM!$L$12/SAM!$AH$12*SUM(SAM!K$23:K$24))/SUM(SAM!$B$23:K$24) -> 0.058998783 | O4: =SUM(SAM!L$3:L$12)/SUM(SAM!AH$3:AH$12) -> 0.066814847 | P4: =(SAM!$L$3/SAM!$AH$3*SAM!$B$23+SAM!$L$4/SAM!$AH$4*SAM!$C$23+SAM!$L$5/SAM!$AH$5*SAM!$D$23+SAM!$L$6/SAM!$AH$6*SAM!$E$23+SAM!$L$7/SAM!$AH$7*SAM!$F$23+SAM!$L$8/SAM!$AH$8*SAM!$G$23+SAM!$L$9/SAM!$AH$9*SAM!$H$23+SAM!$L$10/SAM!$AH$10*SAM!$I$23+SAM!$L$11/SAM!$AH$11*SAM!$J$23+SAM!$L$12/SAM!$AH$12*SAM!$K$23)/SUM(SAM!B$23:K$23) -> 0.059404948 | Q4: =SAM!$AE13/SUM(SAM!AE$13:AE$22) -> 0.14084978 | R4: =(SAM!$AE13-SAM!L$27)/SUM(SAM!$L$3:$L$12) -> 0.39446033 | S4: =SAM!$L$32/SUM(SAM!L$32:U$32) -> 0.046807142 | T4: =SUM(SAM!$L$26,SAM!$L$32)/(SUM(SAM!$L$3:$L$12)-SAM!AE13+SUM(SAM!$L$26,SAM!$L$32)+SUM(SAM!L$28)) -> 0.19668094 | V4: c-agr | W4: =SAM!$B$23/SUM(SAM!$B$23:$B$24) -> 0.619736 | X4: =SAM!$B$24/SUM(SAM!$B$23:$B$24) -> 0.380264 | Y4: =SUM(W4:X4) -> 1 | AA4: c-agr | AB4: =SUM(SAM!B13:K13)/SAM!$AH13 -> 0.50822507 | AC4: =SAM!AC13/SAM!$AH13 -> 0.13090915 | AD4: =SAM!AD13/SAM!$AH13 -> 6.7479526e-05 | AE4: =SAM!AF13/SAM!$AH13 -> 0.01771964 | AF4: =SAM!AG13/SAM!$AH13 -> -0.0001824419 | AG4: =SAM!AE13/SAM!$AH13 -> 0.3432611 | AH4: =SUM(AB4:AG4) -> 1 | AJ4: Impuestos netos | AL4: =SUM(SAM!X31:AB31)/SAM!AH$31 -> 0.9891788
A5: Consumo privado | B5: =SUM(SAM!AC13:AC22) -> 1548.2755 | C5: =B5/$B$12 -> 0.66246569 | E5: Transferencias no gubernamentales | F5: =SAM!AE30 -> -54.682334 | G5: =F5/$B$12 -> -0.023397109 | I5: Impuestos a la producción | J5: =SAM!X31 -> 64.858514 | K5: =J5/$B$12 -> 0.027751225 | M5: c-min | N5: =(SAM!$M$3/SAM!$AH$3*SUM(SAM!B$23:B$24)+SAM!$M$4/SAM!$AH$4*SUM(SAM!C$23:C$24)+SAM!$M$5/SAM!$AH$5*SUM(SAM!D$23:D$24)+SAM!$M$6/SAM!$AH$6*SUM(SAM!E$23:E$24)+SAM!$M$7/SAM!$AH$7*SUM(SAM!F$23:F$24)+SAM!$M$8/SAM!$AH$8*SUM(SAM!G$23:G$24)+SAM!$M$9/SAM!$AH$9*SUM(SAM!H$23:H$24)+SAM!$M$10/SAM!$AH$10*SUM(SAM!I$23:I$24)+SAM!$M$11/SAM!$AH$11*SUM(SAM!J$23:J$24)+SAM!$M$12/SAM!$AH$12*SUM(SAM!K$23:K$24))/SUM(SAM!$B$23:K$24) -> 0.0031783881 | O5: =SUM(SAM!M$3:M$12)/SUM(SAM!AH$3:AH$12) -> 0.0033446388 | P5: =(SAM!$M$3/SAM!$AH$3*SAM!$B$23+SAM!$M$4/SAM!$AH$4*SAM!$C$23+SAM!$M$5/SAM!$AH$5*SAM!$D$23+SAM!$M$6/SAM!$AH$6*SAM!$E$23+SAM!$M$7/SAM!$AH$7*SAM!$F$23+SAM!$M$8/SAM!$AH$8*SAM!$G$23+SAM!$M$9/SAM!$AH$9*SAM!$H$23+SAM!$M$10/SAM!$AH$10*SAM!$I$23+SAM!$M$11/SAM!$AH$11*SAM!$J$23+SAM!$M$12/SAM!$AH$12*SAM!$K$23)/SUM(SAM!B$23:K$23) -> 0.0014784317 | Q5: =SAM!$AE14/SUM(SAM!AE$13:AE$22) -> 0.00027850998 | R5: =(SAM!$AE14-SAM!M$27)/SUM(SAM!$M$3:$M$12) -> 0.015662579 | S5: =SAM!$M$32/SUM(SAM!L$32:U$32) -> 0.0042391885 | T5: =SUM(SAM!$M$26,SAM!$M$32)/(SUM(SAM!$M$3:$M$12)-SAM!AE14+SUM(SAM!$M$26,SAM!$M$32)+SUM(SAM!M$28)) -> 0.20773534 | V5: c-min | W5: =SAM!$C$23/SUM(SAM!$C$23:$C$24) -> 0.28229696 | X5: =SAM!$C$24/SUM(SAM!$C$23:$C$24) -> 0.71770304 | Y5: =SUM(W5:X5) -> 1 | AA5: c-min | AB5: =SUM(SAM!B14:K14)/SAM!$AH14 -> 0.97779762 | AC5: =SAM!AC14/SAM!$AH14 -> 0.011434651 | AD5: =SAM!AD14/SAM!$AH14 -> 0 | AE5: =SAM!AF14/SAM!$AH14 -> 0 | AF5: =SAM!AG14/SAM!$AH14 -> -0.00042597074 | AG5: =SAM!AE14/SAM!$AH14 -> 0.011193696 | AH5: =SUM(AB5:AG5) -> 1 | AJ5: Transferencias del gobierno | AK5: =SAM!AD30/SAM!AH$30 -> -0.024974759
A6: Consumo público | B6: =SUM(SAM!AD13:AD22) -> 399.16571 | C6: =B6/$B$12 -> 0.17079234 | E6: Transferencias gubernamentales | F6: =SAM!AE31 -> 4.0043814 | G6: =F6/$B$12 -> 0.0017133678 | I6: Impuestos al consumo | J6: =SAM!AA31 -> 127.89746 | K6: =J6/$B$12 -> 0.054723906 | M6: c-mnfc | N6: =(SUM(SAM!$N$3:$Q$3)/SAM!$AH$3*SUM(SAM!B$23:B$24)+SUM(SAM!$N$4:$Q$4)/SAM!$AH$4*SUM(SAM!C$23:C$24)+SUM(SAM!$N$5:$Q$5)/SAM!$AH$5*SUM(SAM!D$23:D$24)+SUM(SAM!$N$6:$Q$6)/SAM!$AH$6*SUM(SAM!E$23:E$24)+SUM(SAM!$N$7:$Q$7)/SAM!$AH$7*SUM(SAM!F$23:F$24)+SUM(SAM!$N$8:$Q$8)/SAM!$AH$8*SUM(SAM!G$23:G$24)+SUM(SAM!$N$9:$Q$9)/SAM!$AH$9*SUM(SAM!H$23:H$24)+SUM(SAM!$N$10:$Q$10)/SAM!$AH$10*SUM(SAM!I$23:I$24)+SUM(SAM!$N$11:$Q$11)/SAM!$AH$11*SUM(SAM!J$23:J$24)+SUM(SAM!$N$12:$Q$12)/SAM!$AH$12*SUM(SAM!K$23:K$24))/SUM(SAM!$B$23:K$24) -> 0.14211462 | O6: =SUM(SAM!N$3:Q$12)/SUM(SAM!AH$3:AH$12) -> 0.21563178 | P6: =(SUM(SAM!$N$3:$Q$3)/SAM!$AH$3*SAM!$B$23+SUM(SAM!$N$4:$Q$4)/SAM!$AH$4*SAM!$C$23+SUM(SAM!$N$5:$Q$5)/SAM!$AH$5*SAM!$D$23+SUM(SAM!$N$6:$Q$6)/SAM!$AH$6*SAM!$E$23+SUM(SAM!$N$7:$Q$7)/SAM!$AH$7*SAM!$F$23+SUM(SAM!$N$8:$Q$8)/SAM!$AH$8*SAM!$G$23+SUM(SAM!$N$9:$Q$9)/SAM!$AH$9*SAM!$H$23+SUM(SAM!$N$10:$Q$10)/SAM!$AH$10*SAM!$I$23+SUM(SAM!$N$11:$Q$11)/SAM!$AH$11*SAM!$J$23+SUM(SAM!$N$12:$Q$12)/SAM!$AH$12*SAM!$K$23)/SUM(SAM!$B$23:$K$23) -> 0.10434404 | Q6: =SUM(SAM!$AE15:$AE18)/SUM(SAM!AE$13:AE$22) -> 0.50278944 | R6: =(SUM(SAM!$AE15:$AE18)-SUM(SAM!N$27:Q$27))/SUM(SAM!$N$3:$Q$12) -> 0.43818844 | S6: =SUM(SAM!$N$32:$Q$32)/SUM(SAM!L$32:U$32) -> 0.86152562 | T6: =SUM(SAM!$N$26:$Q$26,SAM!$N$32:$Q$32)/(SUM(SAM!$N$3:$Q$12)-SUM(SAM!AE15:'SAM'!AE18)+SUM(SAM!$N$26:$Q$26,SAM!$N$32:$Q$32)+SUM(SAM!N$28:Q$28)) -> 0.58341988 | V6: c-mnfc | W6: =SUM(SAM!$D$23:$G$23)/SUM(SAM!$D$23:$G$24) -> 0.44233727 | X6: =SUM(SAM!$D$24:'SAM'!$G$24)/SUM(SAM!$D$23:$G$24) -> 0.55766273 | Y6: =SUM(W6:X6) -> 1 | AA6: c-mnfc | AB6: =SUM(SAM!B15:K18)/SUM(SAM!$AH15:$AH18) -> 0.36321842 | AC6: =SUM(SAM!AC15:AC18)/SUM(SAM!$AH15:$AH18) -> 0.34426153 | AD6: =SUM(SAM!AD15:AD18)/SUM(SAM!$AH15:$AH18) -> 0.0058436936 | AE6: =SUM(SAM!AF15:AF18)/SUM(SAM!$AH15:$AH18) -> 0.071328803 | AF6: =SUM(SAM!AG15:AG18)/SUM(SAM!$AH15:$AH18) -> -0.0014256781 | AG6: =SUM(SAM!AE15:AE18)/SUM(SAM!$AH15:$AH18) -> 0.21677323 | AH6: =SUM(AB6:AG6) -> 1 | AJ6: Transferencias del resto del mundo | AK6: =SAM!AE30/SAM!AH$30 -> -0.027786274 | AL6: =SAM!AE31/SAM!AH$31 -> 0.010821201
A7: Formación bruta de capital | B7: =SUM(SAM!AF13:AF22) -> 481.40743 | C7: =B7/$B$12 -> 0.20598137 | E7: Ingresos de factores | F7: =SAM!AE23 -> -1.555335 | G7: =F7/$B$12 -> -0.0006654863 | I7: Impuestos a las importaciones | J7: =SAM!Y31 -> 70.169613 | K7: =J7/$B$12 -> 0.030023702 | M7: c-othind | N7: =(SAM!$R$3/SAM!$AH$3*SUM(SAM!B$23:B$24)+SAM!$R$4/SAM!$AH$4*SUM(SAM!C$23:C$24)+SAM!$R$5/SAM!$AH$5*SUM(SAM!D$23:D$24)+SAM!$R$6/SAM!$AH$6*SUM(SAM!E$23:E$24)+SAM!$R$7/SAM!$AH$7*SUM(SAM!F$23:F$24)+SAM!$R$8/SAM!$AH$8*SUM(SAM!G$23:G$24)+SAM!$R$9/SAM!$AH$9*SUM(SAM!H$23:H$24)+SAM!$R$10/SAM!$AH$10*SUM(SAM!I$23:I$24)+SAM!$R$11/SAM!$AH$11*SUM(SAM!J$23:J$24)+SAM!$R$12/SAM!$AH$12*SUM(SAM!K$23:K$24))/SUM(SAM!$B$23:K$24) -> 0.085261749 | O7: =SUM(SAM!R$3:R$12)/SUM(SAM!AH$3:AH$12) -> 0.12202599 | P7: =(SAM!$R$3/SAM!$AH$3*SAM!$B$23+SAM!$R$4/SAM!$AH$4*SAM!$C$23+SAM!$R$5/SAM!$AH$5*SAM!$D$23+SAM!$R$6/SAM!$AH$6*SAM!$E$23+SAM!$R$7/SAM!$AH$7*SAM!$F$23+SAM!$R$8/SAM!$AH$8*SAM!$G$23+SAM!$R$9/SAM!$AH$9*SAM!$H$23+SAM!$R$10/SAM!$AH$10*SAM!$I$23+SAM!$R$11/SAM!$AH$11*SAM!$J$23+SAM!$R$12/SAM!$AH$12*SAM!$K$23)/SUM(SAM!$B$23:$K$23) -> 0.072535354 | Q7: =SAM!$AE19/SUM(SAM!AE$13:AE$22) -> 0.00069264355 | R7: =(SAM!$AE19-SAM!R$27)/SUM(SAM!$R$3:$R$12) -> 0.0010676507 | S7: =SAM!$R$32/SUM(SAM!L$32:U$32) -> 0.0006380812 | T7: =SUM(SAM!$R$26,SAM!$R$32)/(SUM(SAM!R$3:R$12)-SAM!AE19+SUM(SAM!R$26,SAM!R$32)+SUM(SAM!R$28)) -> 0.0010939234 | V7: c-othind | W7: =SAM!$H$23/SUM(SAM!$H$23:$H$24) -> 0.51856229 | X7: =SAM!$H$24/SUM(SAM!$H$23:$H$24) -> 0.48143771 | Y7: =SUM(W7:X7) -> 1 | AA7: c-othind | AB7: =SUM(SAM!B19:K19)/SAM!$AH19 -> 0.27911786 | AC7: =SAM!AC19/SAM!$AH19 -> 0.092309725 | AD7: =SAM!AD19/SAM!$AH19 -> 0 | AE7: =SAM!AF19/SAM!$AH19 -> 0.62751375 | AF7: =SAM!AG19/SAM!$AH19 -> 0 | AG7: =SAM!AE19/SAM!$AH19 -> 0.0010586607 | AH7: =SUM(AB7:AG7) -> 1 | AJ7: Importaciones | AM7: =SUM(SAM!L32:U32)/SAM!AH$32 -> 1
A8: Variación de existencias | B8: =SUM(SAM!AG13:AG20) -> -2.7704993 | C8: =B8/$B$12 -> -0.0011854226 | E8: Ahorro del resto del mundo | F8: =SAM!AE33 -> 141.1708 | G8: =F8/$B$12 -> 0.060403211 | I8: Impuestos a las exportaciones | J8: =SAM!Z31 -> 0.86586174 | K8: =J8/$B$12 -> 0.0003704791 | M8: c-svc | N8: =(SUM(SAM!$S$3:$U$3)/SAM!$AH$3*SUM(SAM!B$23:B$24)+SUM(SAM!$S$4:$U$4)/SAM!$AH$4*SUM(SAM!C$23:C$24)+SUM(SAM!$S$5:$U$5)/SAM!$AH$5*SUM(SAM!D$23:D$24)+SUM(SAM!$S$6:$U$6)/SAM!$AH$6*SUM(SAM!E$23:E$24)+SUM(SAM!$S$7:$U$7)/SAM!$AH$7*SUM(SAM!F$23:F$24)+SUM(SAM!$S$8:$U$8)/SAM!$AH$8*SUM(SAM!G$23:G$24)+SUM(SAM!$S$9:$U$9)/SAM!$AH$9*SUM(SAM!H$23:H$24)+SUM(SAM!$S$10:$U$10)/SAM!$AH$10*SUM(SAM!I$23:I$24)+SUM(SAM!$S$11:$U$11)/SAM!$AH$11*SUM(SAM!J$23:J$24)+SUM(SAM!$S$12:$U$12)/SAM!$AH$12*SUM(SAM!K$23:K$24))/SUM(SAM!$B$23:K$24) -> 0.71044646 | O8: =SUM(SAM!S$3:U$12)/SUM(SAM!AH$3:AH$12) -> 0.59218274 | P8: =(SUM(SAM!$S$3:$U$3)/SAM!$AH$3*SAM!$B$23+SUM(SAM!$S$4:$U$4)/SAM!$AH$4*SAM!$C$23+SUM(SAM!$S$5:$U$5)/SAM!$AH$5*SAM!$D$23+SUM(SAM!$S$6:$U$6)/SAM!$AH$6*SAM!$E$23+SUM(SAM!$S$7:$U$7)/SAM!$AH$7*SAM!$F$23+SUM(SAM!$S$8:$U$8)/SAM!$AH$8*SAM!$G$23+SUM(SAM!$S$9:$U$9)/SAM!$AH$9*SAM!$H$23+SUM(SAM!$S$10:$U$10)/SAM!$AH$10*SAM!$I$23+SUM(SAM!$S$11:$U$11)/SAM!$AH$11*SAM!$J$23+SUM(SAM!$S$12:$U$12)/SAM!$AH$12*SAM!$K$23)/SUM(SAM!$B$23:$K$23) -> 0.76223723 | Q8: =SUM(SAM!$AE20:$AE22)/SUM(SAM!AE$13:AE$22) -> 0.35538962 | R8: =(SUM(SAM!$AE20:$AE22)-SUM(SAM!S$27:U$27))/SUM(SAM!$S$3:$U$12) -> 0.11288097 | S8: =SUM(SAM!$S$32:$U$32)/SUM(SAM!L$32:U$32) -> 0.086789969 | T8: =SUM(SAM!$S$26:$U$26,SAM!$S$32:$U$32)/(SUM(SAM!$S$3:$U$12)-SUM(SAM!AE20:AE22)+SUM(SAM!$S$26:$U$26,SAM!$S$32:$U$32)+SUM(SAM!S$28:U$28)) -> 0.033052212 | V8: c-svc | W8: =SUM(SAM!$I$23:'SAM'!$K$23)/SUM(SAM!$I$23:$K$24) -> 0.65701885 | X8: =SUM(SAM!$I$24:'SAM'!$K$24)/SUM(SAM!$I$23:$K$24) -> 0.34298115 | Y8: =SUM(W8:X8) -> 1 | AA8: c-svc | AB8: =SUM(SAM!B20:K22)/SUM(SAM!$AH20:$AH22) -> 0.35240583 | AC8: =SUM(SAM!AC20:AC22)/SUM(SAM!$AH20:$AH22) -> 0.35919199 | AD8: =SUM(SAM!AD20:AD22)/SUM(SAM!$AH20:$AH22) -> 0.15985709 | AE8: =SUM(SAM!AF20:AF22)/SUM(SAM!$AH20:$AH22) -> 0.020882012 | AF8: =SUM(SAM!AG20:AG22)/SUM(SAM!$AH20:$AH22) -> -0.00010941588 | AG8: =SUM(SAM!AE20:AE22)/SUM(SAM!$AH20:$AH22) -> 0.1077725 | AH8: =SUM(AB8:AG8) -> 1 | AJ8: Ingresos de trabajo | AK8: =SAM!V30/SAM!AH$30 -> 0.64309498
A9: Cuenta Comercial | B9: =B10-B11 -> -88.937509 | C9: =B9/$B$12 -> -0.038053983 | E9: Total Entradas | F9: =SUM(F4:F8) -> 827.14219 | G9: =F9/$B$12 -> 0.35391204 | I9: Transferencias del resto del mundo | J9: =SAM!AE31 -> 4.0043814 | K9: =J9/$B$12 -> 0.0017133678 | M9: Total | N9: =SUM(N4:N8) -> 1 | O9: =SUM(O4:O8) -> 1 | P9: =SUM(P4:P8) -> 1 | Q9: =SUM(Q4:Q8) -> 1 | R9: =(SUM(SAM!AE13:AE22)-SUM(SAM!L27:U27))/SUM(SAM!L3:U12) -> 0.18787199 | S9: =SUM(S4:S8) -> 1 | T9: =SUM(SAM!L26:U26,SAM!L32:U32)/(SUM(SAM!L3:U12)-SUM(SAM!AE13:AE22)+SUM(SAM!L26:U26,SAM!L32:U32)+SUM(SAM!L$28:U$28)) -> 0.21305257 | V9: Total | W9: =SUM(SAM!B$23:K$23)/SUM(SAM!B$23:K$24) -> 0.61115702 | X9: =SUM(SAM!B$24:K$24)/SUM(SAM!B$23:K$24) -> 0.38884298 | Y9: =SUM(W9:X9) -> 1 | AA9: Total | AB9: =SUM(SAM!B13:K22)/SUM(SAM!$AH13:$AH22) -> 0.3608494 | AC9: =SUM(SAM!AC13:AC22)/SUM(SAM!$AH13:$AH22) -> 0.31273475 | AD9: =SUM(SAM!AD13:AD22)/SUM(SAM!$AH13:$AH22) -> 0.080627119 | AE9: =SUM(SAM!AF13:AF22)/SUM(SAM!$AH13:$AH22) -> 0.097239048 | AF9: =SUM(SAM!AG13:AG22)/SUM(SAM!$AH13:$AH22) -> -0.00055961062 | AG9: =SUM(SAM!AE13:AE22)/SUM(SAM!$AH13:$AH22) -> 0.14910929 | AH9: =SUM(AB9:AG9) -> 1 | AJ9: Ingresos de capital | AK9: =SAM!W30/SAM!AH$30 -> 0.40966605
A10: Exportaciones | B10: =SUM(SAM!AE13:AE22) -> 738.20468 | C10: =B10/$B$12 -> 0.31585806 | E10: Importaciones | F10: =SUM(SAM!L32:U32) -> 827.14219 | G10: =F10/$B$12 -> 0.35391204 | I10: Total Ingresos | J10: =SUM(J4:J9) -> 370.04962 | K10: =J10/$B$12 -> 0.15833434 | AJ10: Total | AK10: =SUM(AK4:AK9) -> 1 | AL10: =SUM(AL4:AL9) -> 1 | AM10: =SUM(AM4:AM9) -> 1
A11: Importaciones | B11: =SUM(SAM!L32:U32) -> 827.14219 | C11: =B11/$B$12 -> 0.35391204 | E11: Total Salidas | F11: =SUM(F10) -> 827.14219 | G11: =F11/$B$12 -> 0.35391204 | I11: Consumo público | J11: =SUM(SAM!AD13:AD22) -> 399.16571 | K11: =J11/$B$12 -> 0.17079234
A12: PBI (a precio de mercado) | B12: =B4+B9 -> 2337.1406 | C12: =B12/$B$12 -> 1 | I12: Transferencias a los hogares | J12: =SAM!AD30 -> -49.149379 | K12: =J12/$B$12 -> -0.021029706
A13: Impuestos indirectos netos | B13: =SUM(SAM!AH25:AH28) -> 263.79145 | C13: =B13/$B$12 -> 0.11286931 | I13: Ahorro del gobierno | J13: =SAM!AD33 -> 20.03329 | K13: =J13/$B$12 -> 0.0085717094
A14: PBI (a costo de factores) | B14: =B12-B13 -> 2073.3491 | C14: =B14/$B$12 -> 0.88713069 | I14: Total Egresos | J14: =SUM(J11:J13) -> 370.04962 | K14: =J14/$B$12 -> 0.15833434

Sheet tables-sim
A1: Tabla 8. Resultados macroeconómicos | H1: Tabla 9. Resultados sectoriales: Valor agregado real | O1: Tabla 10. Resultados sectoriales: Exportaciones reales | V1: Tabla 11. Resultados sectoriales: Importaciones reales | AC1: Tabla 12. Resultados sectoriales: Ventas nacionales reales | AJ1: Tabla 13. Remuneraciones factoriales reales | AQ1: Tabla 14. Resultados de la cuenta corriente de la balanza de pagos | AX1: Tabla 15. Resultados del presupuesto del gobierno
A3: Ítem | B3: base | C3: pwe-othsvc | E3: qg | H3: Actividad | I3: base | J3: pwe-othsvc | L3: qg | O3: Producto | P3: base | Q3: pwe-othsvc | S3: qg | V3: Producto | W3: base | X3: pwe-othsvc | Z3: qg | AC3: Producto | AD3: base | AE3: pwe-othsvc | AG3: qg | AJ3: Factor | AK3: base | AL3: pwe-othsvc | AN3: qg | AQ3: Ítem | AR3: base | AS3: pwe-othsvc | AU3: qg | AX3: Ítem | AY3: base | AZ3: pwe-othsvc | BB3: qg
C4: Nominal | D4: Cambio (%) | E4: Nominal | F4: Cambio (%) | J4: Nominal | K4: Cambio (%) | L4: Nominal | M4: Cambio (%) | Q4: Nominal | R4: Cambio (%) | S4: Nominal | T4: Cambio (%) | X4: Nominal | Y4: Cambio (%) | Z4: Nominal | AA4: Cambio (%) | AE4: Nominal | AF4: Cambio (%) | AG4: Nominal | AH4: Cambio (%) | AL4: Nominal | AM4: Cambio (%) | AN4: Nominal | AO4: Cambio (%) | AS4: Nominal | AT4: Cambio (%) | AU4: Nominal | AV4: Cambio (%) | AZ4: Nominal | BA4: Cambio (%) | BB4: Nominal | BC4: Cambio (%)
A5: Absortion | D5: =C5/$B5-1 -> #DIV/0! | F5: =E5/$B5-1 -> #DIV/0! | H5: a-agr | K5: =J5/$I5-1 -> #DIV/0! | M5: =L5/$I5-1 -> #DIV/0! | O5: c-agr | R5: =Q5/$P5-1 -> #DIV/0! | T5: =S5/$P5-1 -> #DIV/0! | V5: c-agr | Y5: =X5/$W5-1 -> #DIV/0! | AA5: =Z5/$W5-1 -> #DIV/0! | AC5: c-agr | AF5: =AE5/$AD5-1 -> #DIV/0! | AH5: =AG5/$AD5-1 -> #DIV/0! | AJ5: lab | AM5: =AL5/$AK5-1 -> #DIV/0! | AO5: =AN5/$AK5-1 -> #DIV/0! | AQ5: In-Exports | AT5: =AS5/$AR5-1 -> #DIV/0! | AV5: =AU5/$AR5-1 -> #DIV/0! | AX5: Inc-DirTax | BA5: =AZ5/$AY5-1 -> #DIV/0! | BC5: =BB5/$AY5-1 -> #DIV/0!
A6: PrvCon | D6: =C6/$B6-1 -> #DIV/0! | F6: =E6/$B6-1 -> #DIV/0! | H6: a-min | K6: =J6/$I6-1 -> #DIV/0! | M6: =L6/$I6-1 -> #DIV/0! | O6: c-min | R6: =Q6/$P6-1 -> #DIV/0! | T6: =S6/$P6-1 -> #DIV/0! | V6: c-min | Y6: =X6/$W6-1 -> #DIV/0! | AA6: =Z6/$W6-1 -> #DIV/0! | AC6: c-min | AF6: =AE6/$AD6-1 -> #DIV/0! | AH6: =AG6/$AD6-1 -> #DIV/0! | AJ6: cap | AM6: =AL6/$AK6-1 -> #DIV/0! | AO6: =AN6/$AK6-1 -> #DIV/0! | AQ6: In-Trnsfr-NoGov | AT6: =AS6/$AR6-1 -> #DIV/0! | AV6: =AU6/$AR6-1 -> #DIV/0! | AX6: Inc-ActTax | BA6: =AZ6/$AY6-1 -> #DIV/0! | BC6: =BB6/$AY6-1 -> #DIV/0!
A7: GovCon | D7: =C7/$B7-1 -> #DIV/0! | F7: =E7/$B7-1 -> #DIV/0! | H7: a-mnfc | K7: =J7/$I7-1 -> #DIV/0! | M7: =L7/$I7-1 -> #DIV/0! | O7: c-mnfc | R7: =Q7/$P7-1 -> #DIV/0! | T7: =S7/$P7-1 -> #DIV/0! | V7: c-mnfc | Y7: =X7/$W7-1 -> #DIV/0! | AA7: =Z7/$W7-1 -> #DIV/0! | AC7: c-mnfc | AF7: =AE7/$AD7-1 -> #DIV/0! | AH7: =AG7/$AD7-1 -> #DIV/0! | AQ7: In-Trnsfr-Gov | AT7: =AS7/$AR7-1 -> #DIV/0! | AV7: =AU7/$AR7-1 -> #DIV/0! | AX7: Inc-ComTax | BA7: =AZ7/$AY7-1 -> #DIV/0! | BC7: =BB7/$AY7-1 -> #DIV/0!
A8: FixInv | D8: =C8/$B8-1 -> #DIV/0! | F8: =E8/$B8-1 -> #DIV/0! | H8: a-othind | K8: =J8/$I8-1 -> #DIV/0! | M8: =L8/$I8-1 -> #DIV/0! | O8: c-othind | R8: =Q8/$P8-1 -> #DIV/0! | T8: =S8/$P8-1 -> #DIV/0! | V8: c-othind | Y8: =X8/$W8-1 -> #DIV/0! | AA8: =Z8/$W8-1 -> #DIV/0! | AC8: c-othind | AF8: =AE8/$AD8-1 -> #DIV/0! | AH8: =AG8/$AD8-1 -> #DIV/0! | AQ8: In-FacInc | AT8: =AS8/$AR8-1 -> #DIV/0! | AV8: =AU8/$AR8-1 -> #DIV/0! | AX8: Inc-ImpTax | BA8: =AZ8/$AY8-1 -> #DIV/0! | BC8: =BB8/$AY8-1 -> #DIV/0!
A9: StockChange | D9: =C9/$B9-1 -> #DIV/0! | F9: =E9/$B9-1 -> #DIV/0! | H9: a-svc | K9: =J9/$I9-1 -> #DIV/0! | M9: =L9/$I9-1 -> #DIV/0! | O9: c-svc | R9: =Q9/$P9-1 -> #DIV/0! | T9: =S9/$P9-1 -> #DIV/0! | V9: c-svc | Y9: =X9/$W9-1 -> #DIV/0! | AA9: =Z9/$W9-1 -> #DIV/0! | AC9: c-svc | AF9: =AE9/$AD9-1 -> #DIV/0! | AH9: =AG9/$AD9-1 -> #DIV/0! | AQ9: In-RowSav | AT9: =AS9/$AR9-1 -> #DIV/0! | AV9: =AU9/$AR9-1 -> #DIV/0! | AX9: Inc-ExpTax | BA9: =AZ9/$AY9-1 -> #DIV/0! | BC9: =BB9/$AY9-1 -> #DIV/0!
A10: Exports | D10: =C10/$B10-1 -> #DIV/0! | F10: =E10/$B10-1 -> #DIV/0! | H10: Total | I10: =SUM(I5:I9) -> 0 | J10: =SUM(J5:J9) -> 0 | K10: =J10/$I10-1 -> #DIV/0! | L10: =SUM(L5:L9) -> 0 | M10: =L10/$I10-1 -> #DIV/0! | O10: Total | P10: =SUM(P5:P9) -> 0 | Q10: =SUM(Q5:Q9) -> 0 | R10: =Q10/$P10-1 -> #DIV/0! | S10: =SUM(S5:S9) -> 0 | T10: =S10/$P10-1 -> #DIV/0! | V10: Total | W10: =SUM(W5:W9) -> 0 | X10: =SUM(X5:X9) -> 0 | Y10: =X10/$P10-1 -> #DIV/0! | Z10: =SUM(Z5:Z9) -> 0 | AA10: =Z10/$P10-1 -> #DIV/0! | AC10: Total | AD10: =SUM(AD5:AD9) -> 0 | AE10: =SUM(AE5:AE9) -> 0 | AF10: =AE10/$P10-1 -> #DIV/0! | AG10: =SUM(AG5:AG9) -> 0 | AH10: =AG10/$P10-1 -> #DIV/0! | AQ10: In-Total | AR10: =SUM(AR5:AR9) -> 0 | AS10: =SUM(AS5:AS9) -> 0 | AT10: =AS10/$AR10-1 -> #DIV/0! | AU10: =SUM(AU5:AU9) -> 0 | AV10: =AU10/$AR10-1 -> #DIV/0! | AX10: Inc-TrnsfrFor | BA10: =AZ10/$AY10-1 -> #DIV/0! | BC10: =BB10/$AY10-1 -> #DIV/0!
A11: Imports | D11: =C11/$B11-1 -> #DIV/0! | F11: =E11/$B11-1 -> #DIV/0! | AQ11: Out-Imports | AT11: =AS11/$AR11-1 -> #DIV/0! | AV11: =AU11/$AR11-1 -> #DIV/0! | AX11: Inc-Total | AY11: =SUM(AY5:AY10) -> 0 | AZ11: =SUM(AZ5:AZ10) -> 0 | BA11: =AZ11/$AY11-1 -> #DIV/0! | BB11: =SUM(BB5:BB10) -> 0 | BC11: =BB11/$AY11-1 -> #DIV/0!
A12: GDPMP | D12: =C12/$B12-1 -> #DIV/0! | F12: =E12/$B12-1 -> #DIV/0! | AQ12: Out-Total | AR12: =SUM(AR11) -> 0 | AS12: =SUM(AS11) -> 0 | AT12: =AS12/$AR12-1 -> #DIV/0! | AU12: =SUM(AU11) -> 0 | AV12: =AU12/$AR12-1 -> #DIV/0! | AX12: Spnd-GovCon | BA12: =AZ12/$AY12-1 -> #DIV/0! | BC12: =BB12/$AY12-1 -> #DIV/0!
A13: NetIndTax | D13: =C13/$B13-1 -> #DIV/0! | F13: =E13/$B13-1 -> #DIV/0! | AX13: Spnd-TrnsfrDom | BA13: =AZ13/$AY13-1 -> #DIV/0! | BC13: =BB13/$AY13-1 -> #DIV/0!
A14: GDPFC | D14: =C14/$B14-1 -> #DIV/0! | F14: =E14/$B14-1 -> #DIV/0! | AX14: Spnd-GovSav | BA14: =AZ14/$AY14-1 -> #DIV/0! | BC14: =BB14/$AY14-1 -> #DIV/0!
A15: REXR | D15: =C15/$B15-1 -> #DIV/0! | F15: =E15/$B15-1 -> #DIV/0! | AX15: Spnd-Total | AY15: =SUM(AY12:AY14) -> 0 | AZ15: =SUM(AZ12:AZ14) -> 0 | BA15: =AZ15/$AY15-1 -> #DIV/0! | BB15: =SUM(BB12:BB14) -> 0 | BC15: =BB15/$AY15-1 -> #DIV/0!
